odoo8_addon_web_group_expand-8.0.1.0.0.99.dev2-py2.7-nspkg.pth
odoo8_addon_web_group_expand-8.0.1.0.0.99.dev2.dist-info/DESCRIPTION.rst
odoo8_addon_web_group_expand-8.0.1.0.0.99.dev2.dist-info/METADATA
odoo8_addon_web_group_expand-8.0.1.0.0.99.dev2.dist-info/RECORD
odoo8_addon_web_group_expand-8.0.1.0.0.99.dev2.dist-info/WHEEL
odoo8_addon_web_group_expand-8.0.1.0.0.99.dev2.dist-info/metadata.json
odoo8_addon_web_group_expand-8.0.1.0.0.99.dev2.dist-info/namespace_packages.txt
odoo8_addon_web_group_expand-8.0.1.0.0.99.dev2.dist-info/top_level.txt
odoo_addons/web_group_expand/README.rst
odoo_addons/web_group_expand/__init__.py
odoo_addons/web_group_expand/__openerp__.py
odoo_addons/web_group_expand/i18n/web_group_expand.pot
odoo_addons/web_group_expand/static/description/icon.png
odoo_addons/web_group_expand/static/src/css/expand_buttons.css
odoo_addons/web_group_expand/static/src/js/web_group_expand.js
odoo_addons/web_group_expand/static/src/xml/expand_buttons.xml
odoo_addons/web_group_expand/views/templates.xml
