Metadata-Version: 2.0
Name: odoo8-addon-web-group-expand
Version: 8.0.1.0.0.99.dev2
Summary: Group Expand Buttons
Home-page: UNKNOWN
Author: OpenERP SA, AvanzOSC, Serv. Tecnol. Avanzados - Pedro M. Baeza, Odoo Community Association (OCA)
Author-email: support@odoo-community.org
License: UNKNOWN
Platform: UNKNOWN
Classifier: Programming Language :: Python
Classifier: Framework :: Odoo
Requires-Python: ~=2.7
Requires-Dist: odoo (<9.0a,>=8.0a)
